uart_rx.v
module uart_rx(
    input wire clk,
    input wire rst,
    input wire rx,

    output reg [7:0] data_out,
    output reg data_valid,
    output reg framing_error
);

    // FSM States
    parameter IDLE = 3'b000;
    parameter START = 3'b001;
    parameter DATA = 3'b010;
    parameter STOP = 3'b011;
    parameter DONE = 3'b100;

    reg [2:0] state;
    reg [2:0] bit_count;
    reg [7:0] shift_reg;

    always @(posedge clk or posedge rst)
    begin
        if (rst)
        begin
            state <= IDLE;
            bit_count <= 3'd0;
            shift_reg <= 8'd0;
            data_out <= 8'd0;
            data_valid <= 1'b0;
            framing_error <= 1'b0;
        end
        else
        begin
            case(state)

                IDLE:
                begin
                    data_valid <= 1'b0;
                    framing_error <= 1'b0;

                    if(rx == 1'b0)
                        state <= START;
                end

                START:
                begin
                    bit_count <= 3'd0;
                    state <= DATA;
                end

                DATA:
                begin
                    shift_reg[bit_count] <= rx;

                    if(bit_count == 3'd7)
                        state <= STOP;
                    else
                        bit_count <= bit_count + 1;
                end

                STOP:
                begin
                    if(rx == 1'b1)
                    begin
                        data_out <= shift_reg;
                        data_valid <= 1'b1;
                        framing_error <= 1'b0;
                    end
                    else
                    begin
                        framing_error <= 1'b1;
                    end

                    state <= DONE;
                end

                DONE:
                begin
                    state <= IDLE;
                end

                default:
                    state <= IDLE;

            endcase
        end
    end

endmodule

tb_uart_rx.v
`timescale 1ns/1ps

module tb_uart_rx;

    reg clk;
    reg rst;
    reg rx;

    wire [7:0] data_out;
    wire data_valid;
    wire framing_error;

    uart_rx uut (
        .clk(clk),
        .rst(rst),
        .rx(rx),
        .data_out(data_out),
        .data_valid(data_valid),
        .framing_error(framing_error)
    );

    // Clock generation (10 ns period)
    always #5 clk = ~clk;

    // Task to send one UART byte
    task send_byte;
        input [7:0] data;
        integer i;
        begin
            // Start bit
            rx = 0;
            #10;

            // Data bits (LSB first)
            for(i = 0; i < 8; i = i + 1)
            begin
                rx = data[i];
                #10;
            end

            // Stop bit
            rx = 1;
            #10;
        end
    endtask

    initial begin

        $dumpfile("uart.vcd");
        $dumpvars(0, tb_uart_rx);

        clk = 0;
        rst = 1;
        rx = 1;

        #20;
        rst = 0;

        // Send 0xA5 (10100101)
        send_byte(8'hA5);

        #100;

        $finish;

    end

endmodule

uart.vcd
$date
	Sun Jul 19 04:35:11 2026
$end
$version
	Icarus Verilog
$end
$timescale
	1ps
$end
$scope module tb_uart_rx $end
$var wire 1 ! framing_error $end
$var wire 1 " data_valid $end
$var wire 8 # data_out [7:0] $end
$var reg 1 $ clk $end
$var reg 1 % rst $end
$var reg 1 & rx $end
$scope module uut $end
$var wire 1 $ clk $end
$var wire 1 % rst $end
$var wire 1 & rx $end
$var parameter 3 ' DATA $end
$var parameter 3 ( DONE $end
$var parameter 3 ) IDLE $end
$var parameter 3 * START $end
$var parameter 3 + STOP $end
$var reg 3 , bit_count [2:0] $end
$var reg 8 - data_out [7:0] $end
$var reg 1 " data_valid $end
$var reg 1 ! framing_error $end
$var reg 8 . shift_reg [7:0] $end
$var reg 3 / state [2:0] $end
$upscope $end
$scope task send_byte $end
$var reg 8 0 data [7:0] $end
$var integer 32 1 i [31:0] $end
$upscope $end
$upscope $end
$enddefinitions $end
$comment Show the parameter values. $end
$dumpall
b11 +
b1 *
b0 )
b100 (
b10 '
$end
#0
$dumpvars
bx 1
bx 0
b0 /
b0 .
b0 -
b0 ,
1&
1%
0$
b0 #
0"
0!
$end
#5000
1$
#10000
0$
#15000
1$
#20000
0$
0&
b10100101 0
0%
#25000
b1 /
1$
#30000
0$
1&
b0 1
#35000
b10 /
1$
#40000
0$
0&
b1 1
#45000
b1 ,
1$
#50000
0$
1&
b10 1
#55000
b10 ,
b10 .
1$
#60000
0$
0&
b11 1
#65000
b11 ,
1$
#70000
0$
b100 1
#75000
b100 ,
1$
#80000
0$
1&
b101 1
#85000
b101 ,
b10010 .
1$
#90000
0$
0&
b110 1
#95000
b110 ,
1$
#100000
0$
1&
b111 1
#105000
b111 ,
b1010010 .
1$
#110000
0$
b1000 1
#115000
b11 /
b11010010 .
1$
#120000
0$
#125000
b100 /
1"
b11010010 #
b11010010 -
1$
#130000
0$
#135000
b0 /
1$
#140000
0$
#145000
0"
1$
